bigiq_discovery/__init__.py
bigiq_discovery/__main__.py
bigiq_discovery/api.py
bigiq_discovery/collector.py
bigiq_discovery/environments.py
bigiq_discovery/exceptions.py
bigiq_discovery/f5_cluster.py
bigiq_discovery/file_service_discovery.py
bigiq_discovery/fmglogging.py
bigiq_discovery/http_service_discovery.py
bigiq_discovery/metrics.py
bigiq_discovery/transform.py
bigiq_discovery-0.2.0.dist-info/LICENSE
bigiq_discovery-0.2.0.dist-info/METADATA
bigiq_discovery-0.2.0.dist-info/NOTICE
bigiq_discovery-0.2.0.dist-info/WHEEL
bigiq_discovery-0.2.0.dist-info/top_level.txt
bigiq_discovery-0.2.0.dist-info/RECORD
