Metadata-Version: 2.1
Name: bigiq-discovery
Version: 0.2.0
Summary: A Prometheus file and http discovery for .......
Home-page: https://github.com/thenodon/temp-discovery
Author: thenodon
Author-email: aha@ingby.com
License: GPLv3
Requires-Python: >=3.8
License-File: LICENSE
License-File: NOTICE
Requires-Dist: requests ~=2.25.1
Requires-Dist: urllib3 ~=1.26.10
Requires-Dist: PyYAML ~=6.0
Requires-Dist: fastapi ~=0.95.0
Requires-Dist: uvicorn ~=0.21.1
Requires-Dist: python-dateutil ~=2.8.2
Requires-Dist: prometheus-fastapi-instrumentator
Requires-Dist: setuptools ~=60.2.0
Requires-Dist: f5-sdk-python ==0.9.2
